<?xml version="1.0" encoding="UTF-8"?><AutomationReportViewer><TestSuite ActualStatus="FAIL" Duration="00:06:30" EndTime="22/07/2022 12:45:34 PM" ExpectedStatus="PASS" FinalStatus="FAIL" ID="1" Name="DPW_POCSuite" StartTime="22/07/2022 12:39:04 PM"><TestCase ActualStatus="FAIL" Duration="00:00:09" EndTime="22/07/2022 12:39:13 PM" ExpectedStatus="PASS" FinalStatus="FAIL" ID="1" Name="Create Admin_SR Flow_VBCS_Fail" StartTime="22/07/2022 12:39:04 PM"><TestStep ActualStatus="PASS" Duration="00:00:00" EndTime="22/07/2022 12:39:04 PM" ExpectedStatus="PASS" FinalStatus="PASS" ID="1" Name="Application launched succesfully" StartTime="22/07/2022 12:39:04 PM"><Log Duration="00:00:00" EndTime="22/07/2022 12:39:04 PM" Name="LAUNCHBROWSER" StartTime="22/07/2022 12:39:04 PM" Status="PASS" Type="Entered URL to Launch Applicatioin"/></TestStep><TestStep ActualStatus="PASS" Duration="00:00:00" EndTime="22/07/2022 12:39:04 PM" ExpectedStatus="PASS" FinalStatus="PASS" ID="2" Name="Element found SignIn Button" StartTime="22/07/2022 12:39:04 PM"><Log Duration="00:00:00" EndTime="22/07/2022 12:39:04 PM" Name="WAITFORELEMENT" StartTime="22/07/2022 12:39:04 PM" Status="PASS" Type="wait for the element"/></TestStep><TestStep ActualStatus="PASS" Duration="00:00:00" EndTime="22/07/2022 12:39:06 PM" ExpectedStatus="PASS" FinalStatus="PASS" ID="3" Name="Succesfully entered the valueUserId vignesh.sritharan@innovacx.co.in" StartTime="22/07/2022 12:39:06 PM"><Log Duration="00:00:00" EndTime="22/07/2022 12:39:06 PM" Name="ENTERVALUE" StartTime="22/07/2022 12:39:06 PM" Status="PASS" Type="Entere the value in the feild"/></TestStep><TestStep ActualStatus="PASS" Duration="00:00:00" EndTime="22/07/2022 12:39:08 PM" ExpectedStatus="PASS" FinalStatus="PASS" ID="4" Name="Succesfully entered the valuePassword Dpworld@1234" StartTime="22/07/2022 12:39:08 PM"><Log Duration="00:00:00" EndTime="22/07/2022 12:39:08 PM" Name="ENTERVALUE" StartTime="22/07/2022 12:39:08 PM" Status="PASS" Type="Entere the value in the feild"/></TestStep><TestStep ActualStatus="PASS" Duration="00:00:00" EndTime="22/07/2022 12:39:12 PM" ExpectedStatus="PASS" FinalStatus="PASS" ID="5" Name="Succesfully clicked on Sign In" StartTime="22/07/2022 12:39:12 PM"><Log Duration="00:00:00" EndTime="22/07/2022 12:39:12 PM" Name="CLICK" StartTime="22/07/2022 12:39:12 PM" Status="PASS" Type="click on the object"/></TestStep><TestStep ActualStatus="FAIL" Duration="00:00:00" EndTime="22/07/2022 12:39:13 PM" ExpectedStatus="PASS" FinalStatus="FAIL" ID="6" Name="unable to find the locator " StartTime="22/07/2022 12:39:13 PM"><Log Duration="00:00:00" EndTime="22/07/2022 12:39:13 PM" Name="CLICK" Screenshot="img/screenshots/12-39-13Screenshot.jpg" StartTime="22/07/2022 12:39:13 PM" Status="FAIL" Type="click on the object"/></TestStep></TestCase><TestCase ActualStatus="FAIL" Duration="00:06:15" EndTime="22/07/2022 12:45:34 PM" ExpectedStatus="PASS" FinalStatus="FAIL" ID="2" Name="Create Admin_SR Flow_VBCS_Success" StartTime="22/07/2022 12:39:19 PM"><TestStep ActualStatus="PASS" Duration="00:00:00" EndTime="22/07/2022 12:39:19 PM" ExpectedStatus="PASS" FinalStatus="PASS" ID="7" Name="Application launched succesfully" StartTime="22/07/2022 12:39:19 PM"><Log Duration="00:00:00" EndTime="22/07/2022 12:39:19 PM" Name="LAUNCHBROWSER" StartTime="22/07/2022 12:39:19 PM" Status="PASS" Type="Entered URL to Launch Applicatioin"/></TestStep><TestStep ActualStatus="PASS" Duration="00:00:00" EndTime="22/07/2022 12:39:19 PM" ExpectedStatus="PASS" FinalStatus="PASS" ID="8" Name="Element found SignIn Button" StartTime="22/07/2022 12:39:19 PM"><Log Duration="00:00:00" EndTime="22/07/2022 12:39:19 PM" Name="WAITFORELEMENT" StartTime="22/07/2022 12:39:19 PM" Status="PASS" Type="wait for the element"/></TestStep><TestStep ActualStatus="PASS" Duration="00:00:00" EndTime="22/07/2022 12:39:21 PM" ExpectedStatus="PASS" FinalStatus="PASS" ID="9" Name="Succesfully entered the valueUserId vignesh.sritharan@innovacx.com" StartTime="22/07/2022 12:39:21 PM"><Log Duration="00:00:00" EndTime="22/07/2022 12:39:21 PM" Name="ENTERVALUE" StartTime="22/07/2022 12:39:21 PM" Status="PASS" Type="Entere the value in the feild"/></TestStep><TestStep ActualStatus="PASS" Duration="00:00:00" EndTime="22/07/2022 12:39:23 PM" ExpectedStatus="PASS" FinalStatus="PASS" ID="10" Name="Succesfully entered the valuePassword Dpworld@1234" StartTime="22/07/2022 12:39:23 PM"><Log Duration="00:00:00" EndTime="22/07/2022 12:39:23 PM" Name="ENTERVALUE" StartTime="22/07/2022 12:39:23 PM" Status="PASS" Type="Entere the value in the feild"/></TestStep><TestStep ActualStatus="PASS" Duration="00:00:00" EndTime="22/07/2022 12:39:31 PM" ExpectedStatus="PASS" FinalStatus="PASS" ID="11" Name="Succesfully clicked on Sign In" StartTime="22/07/2022 12:39:31 PM"><Log Duration="00:00:00" EndTime="22/07/2022 12:39:31 PM" Name="CLICK" StartTime="22/07/2022 12:39:31 PM" Status="PASS" Type="click on the object"/></TestStep><TestStep ActualStatus="PASS" Duration="00:00:00" EndTime="22/07/2022 12:39:40 PM" ExpectedStatus="PASS" FinalStatus="PASS" ID="12" Name="Succesfully clicked on Home Icon" StartTime="22/07/2022 12:39:40 PM"><Log Duration="00:00:00" EndTime="22/07/2022 12:39:40 PM" Name="CLICK" StartTime="22/07/2022 12:39:40 PM" Status="PASS" Type="click on the object"/></TestStep><TestStep ActualStatus="PASS" Duration="00:00:00" EndTime="22/07/2022 12:39:40 PM" ExpectedStatus="PASS" FinalStatus="PASS" ID="13" Name="Element found Service Request Creation form" StartTime="22/07/2022 12:39:40 PM"><Log Duration="00:00:00" EndTime="22/07/2022 12:39:40 PM" Name="WAITFORELEMENT" StartTime="22/07/2022 12:39:40 PM" Status="PASS" Type="wait for the element"/></TestStep><TestStep ActualStatus="PASS" Duration="00:00:00" EndTime="22/07/2022 12:39:43 PM" ExpectedStatus="PASS" FinalStatus="PASS" ID="14" Name="Succesfully clicked on Service Request Creation form" StartTime="22/07/2022 12:39:43 PM"><Log Duration="00:00:00" EndTime="22/07/2022 12:39:43 PM" Name="CLICK" StartTime="22/07/2022 12:39:43 PM" Status="PASS" Type="click on the object"/></TestStep><TestStep ActualStatus="PASS" Duration="00:00:00" EndTime="22/07/2022 12:40:18 PM" ExpectedStatus="PASS" FinalStatus="PASS" ID="15" Name="Object found in frame  1" StartTime="22/07/2022 12:40:18 PM"><Log Duration="00:00:00" EndTime="22/07/2022 12:40:18 PM" Name="SELECTFRAME" StartTime="22/07/2022 12:40:18 PM" Status="PASS" Type="Select Frame"/></TestStep><TestStep ActualStatus="PASS" Duration="00:00:00" EndTime="22/07/2022 12:40:21 PM" ExpectedStatus="PASS" FinalStatus="PASS" ID="16" Name="Succesfully clicked on Business Unit" StartTime="22/07/2022 12:40:21 PM"><Log Duration="00:00:00" EndTime="22/07/2022 12:40:21 PM" Name="CLICK" StartTime="22/07/2022 12:40:21 PM" Status="PASS" Type="click on the object"/></TestStep><TestStep ActualStatus="PASS" Duration="00:00:00" EndTime="22/07/2022 12:40:22 PM" ExpectedStatus="PASS" FinalStatus="PASS" ID="17" Name="Succesfully clicked on JAFZA" StartTime="22/07/2022 12:40:22 PM"><Log Duration="00:00:00" EndTime="22/07/2022 12:40:22 PM" Name="CLICK" StartTime="22/07/2022 12:40:22 PM" Status="PASS" Type="click on the object"/></TestStep><TestStep ActualStatus="PASS" Duration="00:00:00" EndTime="22/07/2022 12:40:24 PM" ExpectedStatus="PASS" FinalStatus="PASS" ID="18" Name="Succesfully clicked on Process" StartTime="22/07/2022 12:40:24 PM"><Log Duration="00:00:00" EndTime="22/07/2022 12:40:24 PM" Name="CLICK" StartTime="22/07/2022 12:40:24 PM" Status="PASS" Type="click on the object"/></TestStep><TestStep ActualStatus="PASS" Duration="00:00:00" EndTime="22/07/2022 12:40:27 PM" ExpectedStatus="PASS" FinalStatus="PASS" ID="19" Name="Succesfully clicked on Admin" StartTime="22/07/2022 12:40:27 PM"><Log Duration="00:00:00" EndTime="22/07/2022 12:40:27 PM" Name="CLICK" StartTime="22/07/2022 12:40:27 PM" Status="PASS" Type="click on the object"/></TestStep><TestStep ActualStatus="PASS" Duration="00:00:00" EndTime="22/07/2022 12:40:29 PM" ExpectedStatus="PASS" FinalStatus="PASS" ID="20" Name="Succesfully clicked on Sub Process" StartTime="22/07/2022 12:40:29 PM"><Log Duration="00:00:00" EndTime="22/07/2022 12:40:29 PM" Name="CLICK" StartTime="22/07/2022 12:40:29 PM" Status="PASS" Type="click on the object"/></TestStep><TestStep ActualStatus="PASS" Duration="00:00:00" EndTime="22/07/2022 12:40:32 PM" ExpectedStatus="PASS" FinalStatus="PASS" ID="21" Name="Succesfully clicked on Cards" StartTime="22/07/2022 12:40:32 PM"><Log Duration="00:00:00" EndTime="22/07/2022 12:40:32 PM" Name="CLICK" StartTime="22/07/2022 12:40:32 PM" Status="PASS" Type="click on the object"/></TestStep><TestStep ActualStatus="PASS" Duration="00:00:00" EndTime="22/07/2022 12:40:34 PM" ExpectedStatus="PASS" FinalStatus="PASS" ID="22" Name="Succesfully clicked on Search icon" StartTime="22/07/2022 12:40:34 PM"><Log Duration="00:00:00" EndTime="22/07/2022 12:40:34 PM" Name="CLICK" StartTime="22/07/2022 12:40:34 PM" Status="PASS" Type="click on the object"/></TestStep><TestStep ActualStatus="PASS" Duration="00:00:00" EndTime="22/07/2022 12:40:36 PM" ExpectedStatus="PASS" FinalStatus="PASS" ID="23" Name="Object found in frame  1" StartTime="22/07/2022 12:40:36 PM"><Log Duration="00:00:00" EndTime="22/07/2022 12:40:36 PM" Name="SELECTFRAME" StartTime="22/07/2022 12:40:36 PM" Status="PASS" Type="Select Frame"/></TestStep><TestStep ActualStatus="PASS" Duration="00:00:00" EndTime="22/07/2022 12:40:39 PM" ExpectedStatus="PASS" FinalStatus="PASS" ID="24" Name="Succesfully entered the valueCompany name  Rasasi Perfumes Industry FZCO" StartTime="22/07/2022 12:40:39 PM"><Log Duration="00:00:00" EndTime="22/07/2022 12:40:39 PM" Name="ENTERVALUE" StartTime="22/07/2022 12:40:39 PM" Status="PASS" Type="Entere the value in the feild"/></TestStep><TestStep ActualStatus="PASS" Duration="00:00:00" EndTime="22/07/2022 12:40:40 PM" ExpectedStatus="PASS" FinalStatus="PASS" ID="25" Name="Succesfully entered the valueCompany id  1445" StartTime="22/07/2022 12:40:40 PM"><Log Duration="00:00:00" EndTime="22/07/2022 12:40:40 PM" Name="ENTERVALUE" StartTime="22/07/2022 12:40:40 PM" Status="PASS" Type="Entere the value in the feild"/></TestStep><TestStep ActualStatus="PASS" Duration="00:00:00" EndTime="22/07/2022 12:40:42 PM" ExpectedStatus="PASS" FinalStatus="PASS" ID="26" Name="Succesfully clicked on Search Button" StartTime="22/07/2022 12:40:42 PM"><Log Duration="00:00:00" EndTime="22/07/2022 12:40:42 PM" Name="CLICK" StartTime="22/07/2022 12:40:42 PM" Status="PASS" Type="click on the object"/></TestStep><TestStep ActualStatus="PASS" Duration="00:00:00" EndTime="22/07/2022 12:40:47 PM" ExpectedStatus="PASS" FinalStatus="PASS" ID="27" Name="Element found Rasasi Perfumes Industry FZCO Search Result" StartTime="22/07/2022 12:40:47 PM"><Log Duration="00:00:00" EndTime="22/07/2022 12:40:47 PM" Name="WAITFORELEMENT" StartTime="22/07/2022 12:40:47 PM" Status="PASS" Type="wait for the element"/></TestStep><TestStep ActualStatus="PASS" Duration="00:00:00" EndTime="22/07/2022 12:40:50 PM" ExpectedStatus="PASS" FinalStatus="PASS" ID="28" Name="Succesfully clicked on Rasasi Perfumes Industry FZCO" StartTime="22/07/2022 12:40:50 PM"><Log Duration="00:00:00" EndTime="22/07/2022 12:40:50 PM" Name="CLICK" StartTime="22/07/2022 12:40:50 PM" Status="PASS" Type="click on the object"/></TestStep><TestStep ActualStatus="PASS" Duration="00:00:00" EndTime="22/07/2022 12:40:51 PM" ExpectedStatus="PASS" FinalStatus="PASS" ID="29" Name="Element found Jafza Permanent Identity Card New" StartTime="22/07/2022 12:40:51 PM"><Log Duration="00:00:00" EndTime="22/07/2022 12:40:51 PM" Name="WAITFORELEMENT" StartTime="22/07/2022 12:40:51 PM" Status="PASS" Type="wait for the element"/></TestStep><TestStep ActualStatus="PASS" Duration="00:00:00" EndTime="22/07/2022 12:40:54 PM" ExpectedStatus="PASS" FinalStatus="PASS" ID="30" Name="Succesfully clicked on Jafza Permanent Identity Card New" StartTime="22/07/2022 12:40:54 PM"><Log Duration="00:00:00" EndTime="22/07/2022 12:40:54 PM" Name="CLICK" StartTime="22/07/2022 12:40:54 PM" Status="PASS" Type="click on the object"/></TestStep><TestStep ActualStatus="PASS" Duration="00:00:00" EndTime="22/07/2022 12:41:05 PM" ExpectedStatus="PASS" FinalStatus="PASS" ID="31" Name="Succesfully clicked on Create New request button" StartTime="22/07/2022 12:41:05 PM"><Log Duration="00:00:00" EndTime="22/07/2022 12:41:05 PM" Name="CLICK" StartTime="22/07/2022 12:41:05 PM" Status="PASS" Type="click on the object"/></TestStep><TestStep ActualStatus="PASS" Duration="00:00:00" EndTime="22/07/2022 12:41:46 PM" ExpectedStatus="PASS" FinalStatus="PASS" ID="32" Name="Succesfully clicked on Title" StartTime="22/07/2022 12:41:46 PM"><Log Duration="00:00:00" EndTime="22/07/2022 12:41:46 PM" Name="CLICK" StartTime="22/07/2022 12:41:46 PM" Status="PASS" Type="click on the object"/></TestStep><TestStep ActualStatus="PASS" Duration="00:00:00" EndTime="22/07/2022 12:41:47 PM" ExpectedStatus="PASS" FinalStatus="PASS" ID="33" Name="Succesfully clicked on Title value" StartTime="22/07/2022 12:41:47 PM"><Log Duration="00:00:00" EndTime="22/07/2022 12:41:47 PM" Name="CLICK" StartTime="22/07/2022 12:41:47 PM" Status="PASS" Type="click on the object"/></TestStep><TestStep ActualStatus="PASS" Duration="00:00:00" EndTime="22/07/2022 12:41:48 PM" ExpectedStatus="PASS" FinalStatus="PASS" ID="34" Name="Succesfully entered the valueGiven Name  Albert" StartTime="22/07/2022 12:41:48 PM"><Log Duration="00:00:00" EndTime="22/07/2022 12:41:48 PM" Name="ENTERVALUE" StartTime="22/07/2022 12:41:48 PM" Status="PASS" Type="Entere the value in the feild"/></TestStep><TestStep ActualStatus="PASS" Duration="00:00:00" EndTime="22/07/2022 12:41:48 PM" ExpectedStatus="PASS" FinalStatus="PASS" ID="35" Name="Succesfully entered the valueLast Name  Einstein" StartTime="22/07/2022 12:41:48 PM"><Log Duration="00:00:00" EndTime="22/07/2022 12:41:48 PM" Name="ENTERVALUE" StartTime="22/07/2022 12:41:48 PM" Status="PASS" Type="Entere the value in the feild"/></TestStep><TestStep ActualStatus="PASS" Duration="00:00:00" EndTime="22/07/2022 12:41:48 PM" ExpectedStatus="PASS" FinalStatus="PASS" ID="36" Name="captured the value  store Entered Lastname   Einstein" StartTime="22/07/2022 12:41:48 PM"><Log Duration="00:00:00" EndTime="22/07/2022 12:41:48 PM" Name="GETTEXT" StartTime="22/07/2022 12:41:48 PM" Status="PASS" Type="capture the text"/></TestStep><TestStep ActualStatus="PASS" Duration="00:00:00" EndTime="22/07/2022 12:41:49 PM" ExpectedStatus="PASS" FinalStatus="PASS" ID="37" Name="Succesfully clicked on Nationality" StartTime="22/07/2022 12:41:49 PM"><Log Duration="00:00:00" EndTime="22/07/2022 12:41:49 PM" Name="CLICK" StartTime="22/07/2022 12:41:49 PM" Status="PASS" Type="click on the object"/></TestStep><TestStep ActualStatus="PASS" Duration="00:00:00" EndTime="22/07/2022 12:41:57 PM" ExpectedStatus="PASS" FinalStatus="PASS" ID="38" Name="Succesfully clicked on Click:United Arab Emirates" StartTime="22/07/2022 12:41:57 PM"><Log Duration="00:00:00" EndTime="22/07/2022 12:41:57 PM" Name="CLICK" StartTime="22/07/2022 12:41:57 PM" Status="PASS" Type="click on the object"/></TestStep><TestStep ActualStatus="PASS" Duration="00:00:00" EndTime="22/07/2022 12:41:57 PM" ExpectedStatus="PASS" FinalStatus="PASS" ID="39" Name="Succesfully entered the valuebasic salary  5000" StartTime="22/07/2022 12:41:57 PM"><Log Duration="00:00:00" EndTime="22/07/2022 12:41:57 PM" Name="ENTERVALUE" StartTime="22/07/2022 12:41:57 PM" Status="PASS" Type="Entere the value in the feild"/></TestStep><TestStep ActualStatus="PASS" Duration="00:00:01" EndTime="22/07/2022 12:41:59 PM" ExpectedStatus="PASS" FinalStatus="PASS" ID="40" Name="Succesfully clicked on Food provided" StartTime="22/07/2022 12:41:58 PM"><Log Duration="00:00:00" EndTime="22/07/2022 12:41:58 PM" Name="CLICK" StartTime="22/07/2022 12:41:58 PM" Status="PASS" Type="click on the object"/></TestStep><TestStep ActualStatus="PASS" Duration="00:00:00" EndTime="22/07/2022 12:42:00 PM" ExpectedStatus="PASS" FinalStatus="PASS" ID="41" Name="Succesfully clicked on Yes" StartTime="22/07/2022 12:42:00 PM"><Log Duration="00:00:00" EndTime="22/07/2022 12:42:00 PM" Name="CLICK" StartTime="22/07/2022 12:42:00 PM" Status="PASS" Type="click on the object"/></TestStep><TestStep ActualStatus="PASS" Duration="00:00:00" EndTime="22/07/2022 12:42:01 PM" ExpectedStatus="PASS" FinalStatus="PASS" ID="42" Name="Succesfully clicked on Accomidation Provided" StartTime="22/07/2022 12:42:01 PM"><Log Duration="00:00:00" EndTime="22/07/2022 12:42:01 PM" Name="CLICK" StartTime="22/07/2022 12:42:01 PM" Status="PASS" Type="click on the object"/></TestStep><TestStep ActualStatus="PASS" Duration="00:00:00" EndTime="22/07/2022 12:42:02 PM" ExpectedStatus="PASS" FinalStatus="PASS" ID="43" Name="Succesfully clicked on Yes" StartTime="22/07/2022 12:42:02 PM"><Log Duration="00:00:00" EndTime="22/07/2022 12:42:02 PM" Name="CLICK" StartTime="22/07/2022 12:42:02 PM" Status="PASS" Type="click on the object"/></TestStep><TestStep ActualStatus="PASS" Duration="00:00:00" EndTime="22/07/2022 12:42:03 PM" ExpectedStatus="PASS" FinalStatus="PASS" ID="44" Name="Succesfully clicked on Accomidation Type" StartTime="22/07/2022 12:42:03 PM"><Log Duration="00:00:00" EndTime="22/07/2022 12:42:03 PM" Name="CLICK" StartTime="22/07/2022 12:42:03 PM" Status="PASS" Type="click on the object"/></TestStep><TestStep ActualStatus="PASS" Duration="00:00:00" EndTime="22/07/2022 12:42:05 PM" ExpectedStatus="PASS" FinalStatus="PASS" ID="45" Name="Succesfully clicked on Family" StartTime="22/07/2022 12:42:05 PM"><Log Duration="00:00:00" EndTime="22/07/2022 12:42:05 PM" Name="CLICK" StartTime="22/07/2022 12:42:05 PM" Status="PASS" Type="click on the object"/></TestStep><TestStep ActualStatus="PASS" Duration="00:00:00" EndTime="22/07/2022 12:42:06 PM" ExpectedStatus="PASS" FinalStatus="PASS" ID="46" Name="Succesfully clicked on Transportation Provided" StartTime="22/07/2022 12:42:06 PM"><Log Duration="00:00:00" EndTime="22/07/2022 12:42:06 PM" Name="CLICK" StartTime="22/07/2022 12:42:06 PM" Status="PASS" Type="click on the object"/></TestStep><TestStep ActualStatus="PASS" Duration="00:00:00" EndTime="22/07/2022 12:42:07 PM" ExpectedStatus="PASS" FinalStatus="PASS" ID="47" Name="Succesfully clicked on No" StartTime="22/07/2022 12:42:07 PM"><Log Duration="00:00:00" EndTime="22/07/2022 12:42:07 PM" Name="CLICK" StartTime="22/07/2022 12:42:07 PM" Status="PASS" Type="click on the object"/></TestStep><TestStep ActualStatus="PASS" Duration="00:00:00" EndTime="22/07/2022 12:42:07 PM" ExpectedStatus="PASS" FinalStatus="PASS" ID="48" Name="Succesfully entered the valueMonthly Allowance  3000" StartTime="22/07/2022 12:42:07 PM"><Log Duration="00:00:00" EndTime="22/07/2022 12:42:07 PM" Name="ENTERVALUE" StartTime="22/07/2022 12:42:07 PM" Status="PASS" Type="Entere the value in the feild"/></TestStep><TestStep ActualStatus="PASS" Duration="00:00:00" EndTime="22/07/2022 12:42:09 PM" ExpectedStatus="PASS" FinalStatus="PASS" ID="49" Name="Succesfully clicked on Religion" StartTime="22/07/2022 12:42:09 PM"><Log Duration="00:00:00" EndTime="22/07/2022 12:42:09 PM" Name="CLICK" StartTime="22/07/2022 12:42:09 PM" Status="PASS" Type="click on the object"/></TestStep><TestStep ActualStatus="PASS" Duration="00:00:00" EndTime="22/07/2022 12:42:10 PM" ExpectedStatus="PASS" FinalStatus="PASS" ID="50" Name="Succesfully clicked on Hindu" StartTime="22/07/2022 12:42:10 PM"><Log Duration="00:00:00" EndTime="22/07/2022 12:42:10 PM" Name="CLICK" StartTime="22/07/2022 12:42:10 PM" Status="PASS" Type="click on the object"/></TestStep><TestStep ActualStatus="PASS" Duration="00:00:00" EndTime="22/07/2022 12:42:10 PM" ExpectedStatus="PASS" FinalStatus="PASS" ID="51" Name="Succesfully entered the valueplace of birth  Dubai" StartTime="22/07/2022 12:42:10 PM"><Log Duration="00:00:00" EndTime="22/07/2022 12:42:10 PM" Name="ENTERVALUE" StartTime="22/07/2022 12:42:10 PM" Status="PASS" Type="Entere the value in the feild"/></TestStep><TestStep ActualStatus="PASS" Duration="00:00:00" EndTime="22/07/2022 12:42:11 PM" ExpectedStatus="PASS" FinalStatus="PASS" ID="52" Name="Succesfully clicked on DOB" StartTime="22/07/2022 12:42:11 PM"><Log Duration="00:00:00" EndTime="22/07/2022 12:42:11 PM" Name="CLICK" StartTime="22/07/2022 12:42:11 PM" Status="PASS" Type="click on the object"/></TestStep><TestStep ActualStatus="PASS" Duration="00:00:00" EndTime="22/07/2022 12:42:12 PM" ExpectedStatus="PASS" FinalStatus="PASS" ID="53" Name="Succesfully clicked on 01-Mar-2003" StartTime="22/07/2022 12:42:12 PM"><Log Duration="00:00:00" EndTime="22/07/2022 12:42:12 PM" Name="CLICK" StartTime="22/07/2022 12:42:12 PM" Status="PASS" Type="click on the object"/></TestStep><TestStep ActualStatus="PASS" Duration="00:00:00" EndTime="22/07/2022 12:42:14 PM" ExpectedStatus="PASS" FinalStatus="PASS" ID="54" Name="Succesfully clicked on Marrital Status" StartTime="22/07/2022 12:42:14 PM"><Log Duration="00:00:00" EndTime="22/07/2022 12:42:14 PM" Name="CLICK" StartTime="22/07/2022 12:42:14 PM" Status="PASS" Type="click on the object"/></TestStep><TestStep ActualStatus="PASS" Duration="00:00:00" EndTime="22/07/2022 12:42:15 PM" ExpectedStatus="PASS" FinalStatus="PASS" ID="55" Name="Succesfully clicked on SignIn Button" StartTime="22/07/2022 12:42:15 PM"><Log Duration="00:00:00" EndTime="22/07/2022 12:42:15 PM" Name="CLICK" StartTime="22/07/2022 12:42:15 PM" Status="PASS" Type="click on the object"/></TestStep><TestStep ActualStatus="PASS" Duration="00:00:00" EndTime="22/07/2022 12:42:16 PM" ExpectedStatus="PASS" FinalStatus="PASS" ID="56" Name="Succesfully clicked on Card Validity" StartTime="22/07/2022 12:42:16 PM"><Log Duration="00:00:00" EndTime="22/07/2022 12:42:16 PM" Name="CLICK" StartTime="22/07/2022 12:42:16 PM" Status="PASS" Type="click on the object"/></TestStep><TestStep ActualStatus="PASS" Duration="00:00:00" EndTime="22/07/2022 12:42:17 PM" ExpectedStatus="PASS" FinalStatus="PASS" ID="57" Name="Succesfully clicked on 2 years" StartTime="22/07/2022 12:42:17 PM"><Log Duration="00:00:00" EndTime="22/07/2022 12:42:17 PM" Name="CLICK" StartTime="22/07/2022 12:42:17 PM" Status="PASS" Type="click on the object"/></TestStep><TestStep ActualStatus="PASS" Duration="00:00:00" EndTime="22/07/2022 12:42:18 PM" ExpectedStatus="PASS" FinalStatus="PASS" ID="58" Name="Succesfully clicked on Job Title" StartTime="22/07/2022 12:42:18 PM"><Log Duration="00:00:00" EndTime="22/07/2022 12:42:18 PM" Name="CLICK" StartTime="22/07/2022 12:42:18 PM" Status="PASS" Type="click on the object"/></TestStep><TestStep ActualStatus="PASS" Duration="00:00:00" EndTime="22/07/2022 12:42:20 PM" ExpectedStatus="PASS" FinalStatus="PASS" ID="59" Name="Succesfully clicked on 1St COMMIS" StartTime="22/07/2022 12:42:20 PM"><Log Duration="00:00:00" EndTime="22/07/2022 12:42:20 PM" Name="CLICK" StartTime="22/07/2022 12:42:20 PM" Status="PASS" Type="click on the object"/></TestStep><TestStep ActualStatus="PASS" Duration="00:00:00" EndTime="22/07/2022 12:42:20 PM" ExpectedStatus="PASS" FinalStatus="PASS" ID="60" Name="ABC2106185" StartTime="22/07/2022 12:42:20 PM"><Log Duration="00:00:00" EndTime="22/07/2022 12:42:20 PM" Name="GENERATE_UNIQVALUE" StartTime="22/07/2022 12:42:20 PM" Status="PASS" Type="Generated Uniq Value Number  "/></TestStep><TestStep ActualStatus="PASS" Duration="00:00:00" EndTime="22/07/2022 12:42:20 PM" ExpectedStatus="PASS" FinalStatus="PASS" ID="61" Name="Succesfully entered the valuePassport_Number ABC2106185" StartTime="22/07/2022 12:42:20 PM"><Log Duration="00:00:00" EndTime="22/07/2022 12:42:20 PM" Name="ENTERVALUE" StartTime="22/07/2022 12:42:20 PM" Status="PASS" Type="Entere the value in the feild"/></TestStep><TestStep ActualStatus="PASS" Duration="00:00:00" EndTime="22/07/2022 12:42:22 PM" ExpectedStatus="PASS" FinalStatus="PASS" ID="62" Name="captured the value  Store Passport_Number   ABC2106185" StartTime="22/07/2022 12:42:22 PM"><Log Duration="00:00:00" EndTime="22/07/2022 12:42:22 PM" Name="GETTEXT" StartTime="22/07/2022 12:42:22 PM" Status="PASS" Type="capture the text"/></TestStep><TestStep ActualStatus="PASS" Duration="00:00:00" EndTime="22/07/2022 12:42:22 PM" ExpectedStatus="PASS" FinalStatus="PASS" ID="63" Name="Succesfully entered the valueISSUE Date  01-Apr-2021" StartTime="22/07/2022 12:42:22 PM"><Log Duration="00:00:00" EndTime="22/07/2022 12:42:22 PM" Name="ENTERVALUE" StartTime="22/07/2022 12:42:22 PM" Status="PASS" Type="Entere the value in the feild"/></TestStep><TestStep ActualStatus="PASS" Duration="00:00:00" EndTime="22/07/2022 12:42:22 PM" ExpectedStatus="PASS" FinalStatus="PASS" ID="64" Name="Successfully clicked on ENTER" StartTime="22/07/2022 12:42:22 PM"><Log Duration="00:00:00" EndTime="22/07/2022 12:42:22 PM" Name="SENDKEYS" StartTime="22/07/2022 12:42:22 PM" Status="PASS" Type="send keys"/><Log Duration="00:00:00" EndTime="22/07/2022 12:42:22 PM" Name="SENDKEYS" StartTime="22/07/2022 12:42:22 PM" Status="PASS" Type="send keys"/></TestStep><TestStep ActualStatus="PASS" Duration="00:00:00" EndTime="22/07/2022 12:42:25 PM" ExpectedStatus="PASS" FinalStatus="PASS" ID="65" Name="Succesfully entered the valueEXPIRY Date  10-Aug-2023" StartTime="22/07/2022 12:42:25 PM"><Log Duration="00:00:00" EndTime="22/07/2022 12:42:25 PM" Name="ENTERVALUE" StartTime="22/07/2022 12:42:25 PM" Status="PASS" Type="Entere the value in the feild"/></TestStep><TestStep ActualStatus="PASS" Duration="00:00:00" EndTime="22/07/2022 12:42:25 PM" ExpectedStatus="PASS" FinalStatus="PASS" ID="66" Name="Successfully clicked on ENTER" StartTime="22/07/2022 12:42:25 PM"><Log Duration="00:00:00" EndTime="22/07/2022 12:42:25 PM" Name="SENDKEYS" StartTime="22/07/2022 12:42:25 PM" Status="PASS" Type="send keys"/><Log Duration="00:00:00" EndTime="22/07/2022 12:42:25 PM" Name="SENDKEYS" StartTime="22/07/2022 12:42:25 PM" Status="PASS" Type="send keys"/></TestStep><TestStep ActualStatus="PASS" Duration="00:00:00" EndTime="22/07/2022 12:42:27 PM" ExpectedStatus="PASS" FinalStatus="PASS" ID="67" Name="Succesfully entered the valuePlace Of Issue  Dubai" StartTime="22/07/2022 12:42:27 PM"><Log Duration="00:00:00" EndTime="22/07/2022 12:42:27 PM" Name="ENTERVALUE" StartTime="22/07/2022 12:42:27 PM" Status="PASS" Type="Entere the value in the feild"/></TestStep><TestStep ActualStatus="PASS" Duration="00:00:00" EndTime="22/07/2022 12:42:28 PM" ExpectedStatus="PASS" FinalStatus="PASS" ID="68" Name="Succesfully clicked on Country Of Issue" StartTime="22/07/2022 12:42:28 PM"><Log Duration="00:00:00" EndTime="22/07/2022 12:42:28 PM" Name="CLICK" StartTime="22/07/2022 12:42:28 PM" Status="PASS" Type="click on the object"/></TestStep><TestStep ActualStatus="PASS" Duration="00:00:00" EndTime="22/07/2022 12:42:34 PM" ExpectedStatus="PASS" FinalStatus="PASS" ID="69" Name="Succesfully clicked on United Arab Emirates" StartTime="22/07/2022 12:42:34 PM"><Log Duration="00:00:00" EndTime="22/07/2022 12:42:34 PM" Name="CLICK" StartTime="22/07/2022 12:42:34 PM" Status="PASS" Type="click on the object"/></TestStep><TestStep ActualStatus="PASS" Duration="00:00:00" EndTime="22/07/2022 12:42:34 PM" ExpectedStatus="PASS" FinalStatus="PASS" ID="70" Name="Succesfully entered the valueAddress1  Flat 101,street1,new2" StartTime="22/07/2022 12:42:34 PM"><Log Duration="00:00:00" EndTime="22/07/2022 12:42:34 PM" Name="ENTERVALUE" StartTime="22/07/2022 12:42:34 PM" Status="PASS" Type="Entere the value in the feild"/></TestStep><TestStep ActualStatus="PASS" Duration="00:00:00" EndTime="22/07/2022 12:42:35 PM" ExpectedStatus="PASS" FinalStatus="PASS" ID="71" Name="Succesfully entered the valuePO BOX  Dubai" StartTime="22/07/2022 12:42:35 PM"><Log Duration="00:00:00" EndTime="22/07/2022 12:42:35 PM" Name="ENTERVALUE" StartTime="22/07/2022 12:42:35 PM" Status="PASS" Type="Entere the value in the feild"/></TestStep><TestStep ActualStatus="PASS" Duration="00:00:00" EndTime="22/07/2022 12:42:36 PM" ExpectedStatus="PASS" FinalStatus="PASS" ID="72" Name="Succesfully clicked on Permanent Country" StartTime="22/07/2022 12:42:36 PM"><Log Duration="00:00:00" EndTime="22/07/2022 12:42:36 PM" Name="CLICK" StartTime="22/07/2022 12:42:36 PM" Status="PASS" Type="click on the object"/></TestStep><TestStep ActualStatus="PASS" Duration="00:00:00" EndTime="22/07/2022 12:42:43 PM" ExpectedStatus="PASS" FinalStatus="PASS" ID="73" Name="Succesfully clicked on United Arab Emirates" StartTime="22/07/2022 12:42:43 PM"><Log Duration="00:00:00" EndTime="22/07/2022 12:42:43 PM" Name="CLICK" StartTime="22/07/2022 12:42:43 PM" Status="PASS" Type="click on the object"/></TestStep><TestStep ActualStatus="PASS" Duration="00:00:00" EndTime="22/07/2022 12:42:44 PM" ExpectedStatus="PASS" FinalStatus="PASS" ID="74" Name="Succesfully entered the valueEIDA Number  234-5678-2314563-8" StartTime="22/07/2022 12:42:44 PM"><Log Duration="00:00:00" EndTime="22/07/2022 12:42:44 PM" Name="ENTERVALUE" StartTime="22/07/2022 12:42:44 PM" Status="PASS" Type="Entere the value in the feild"/></TestStep><TestStep ActualStatus="PASS" Duration="00:00:00" EndTime="22/07/2022 12:42:44 PM" ExpectedStatus="PASS" FinalStatus="PASS" ID="75" Name="Succesfully entered the valueSponsor Address  Flat 195,street10,Test" StartTime="22/07/2022 12:42:44 PM"><Log Duration="00:00:00" EndTime="22/07/2022 12:42:44 PM" Name="ENTERVALUE" StartTime="22/07/2022 12:42:44 PM" Status="PASS" Type="Entere the value in the feild"/></TestStep><TestStep ActualStatus="PASS" Duration="00:00:00" EndTime="22/07/2022 12:42:45 PM" ExpectedStatus="PASS" FinalStatus="PASS" ID="76" Name="Succesfully clicked on Sponsor Emirate" StartTime="22/07/2022 12:42:45 PM"><Log Duration="00:00:00" EndTime="22/07/2022 12:42:45 PM" Name="CLICK" StartTime="22/07/2022 12:42:45 PM" Status="PASS" Type="click on the object"/></TestStep><TestStep ActualStatus="PASS" Duration="00:00:00" EndTime="22/07/2022 12:42:47 PM" ExpectedStatus="PASS" FinalStatus="PASS" ID="77" Name="Succesfully clicked on Dubai" StartTime="22/07/2022 12:42:47 PM"><Log Duration="00:00:00" EndTime="22/07/2022 12:42:47 PM" Name="CLICK" StartTime="22/07/2022 12:42:47 PM" Status="PASS" Type="click on the object"/></TestStep><TestStep ActualStatus="PASS" Duration="00:00:00" EndTime="22/07/2022 12:42:47 PM" ExpectedStatus="PASS" FinalStatus="PASS" ID="78" Name="Succesfully entered the valuePO BOX No  347" StartTime="22/07/2022 12:42:47 PM"><Log Duration="00:00:00" EndTime="22/07/2022 12:42:47 PM" Name="ENTERVALUE" StartTime="22/07/2022 12:42:47 PM" Status="PASS" Type="Entere the value in the feild"/></TestStep><TestStep ActualStatus="PASS" Duration="00:00:00" EndTime="22/07/2022 12:42:47 PM" ExpectedStatus="PASS" FinalStatus="PASS" ID="79" Name="Succesfully entered the valueCoContact name  Rachelem" StartTime="22/07/2022 12:42:47 PM"><Log Duration="00:00:00" EndTime="22/07/2022 12:42:47 PM" Name="ENTERVALUE" StartTime="22/07/2022 12:42:47 PM" Status="PASS" Type="Entere the value in the feild"/></TestStep><TestStep ActualStatus="PASS" Duration="00:00:00" EndTime="22/07/2022 12:42:47 PM" ExpectedStatus="PASS" FinalStatus="PASS" ID="80" Name="Succesfully entered the valueRequest Reason  TESt test TESting" StartTime="22/07/2022 12:42:47 PM"><Log Duration="00:00:00" EndTime="22/07/2022 12:42:47 PM" Name="ENTERVALUE" StartTime="22/07/2022 12:42:47 PM" Status="PASS" Type="Entere the value in the feild"/></TestStep><TestStep ActualStatus="PASS" Duration="00:00:00" EndTime="22/07/2022 12:42:48 PM" ExpectedStatus="PASS" FinalStatus="PASS" ID="81" Name="Succesfully entered the valueContact Name  Michel" StartTime="22/07/2022 12:42:48 PM"><Log Duration="00:00:00" EndTime="22/07/2022 12:42:48 PM" Name="ENTERVALUE" StartTime="22/07/2022 12:42:48 PM" Status="PASS" Type="Entere the value in the feild"/></TestStep><TestStep ActualStatus="PASS" Duration="00:00:00" EndTime="22/07/2022 12:42:48 PM" ExpectedStatus="PASS" FinalStatus="PASS" ID="82" Name="Succesfully entered the valueContact Phone  0565743587" StartTime="22/07/2022 12:42:48 PM"><Log Duration="00:00:00" EndTime="22/07/2022 12:42:48 PM" Name="ENTERVALUE" StartTime="22/07/2022 12:42:48 PM" Status="PASS" Type="Entere the value in the feild"/></TestStep><TestStep ActualStatus="PASS" Duration="00:00:00" EndTime="22/07/2022 12:42:49 PM" ExpectedStatus="PASS" FinalStatus="PASS" ID="83" Name="Succesfully clicked on Time" StartTime="22/07/2022 12:42:49 PM"><Log Duration="00:00:00" EndTime="22/07/2022 12:42:49 PM" Name="CLICK" StartTime="22/07/2022 12:42:49 PM" Status="PASS" Type="click on the object"/></TestStep><TestStep ActualStatus="PASS" Duration="00:00:00" EndTime="22/07/2022 12:42:50 PM" ExpectedStatus="PASS" FinalStatus="PASS" ID="84" Name="Succesfully clicked on 9AM-11AM" StartTime="22/07/2022 12:42:50 PM"><Log Duration="00:00:00" EndTime="22/07/2022 12:42:50 PM" Name="CLICK" StartTime="22/07/2022 12:42:50 PM" Status="PASS" Type="click on the object"/></TestStep><TestStep ActualStatus="PASS" Duration="00:00:00" EndTime="22/07/2022 12:42:53 PM" ExpectedStatus="PASS" FinalStatus="PASS" ID="85" Name="Succesfully clicked on Save&amp;Continue" StartTime="22/07/2022 12:42:53 PM"><Log Duration="00:00:00" EndTime="22/07/2022 12:42:53 PM" Name="CLICK" StartTime="22/07/2022 12:42:53 PM" Status="PASS" Type="click on the object"/></TestStep><TestStep ActualStatus="PASS" Duration="00:00:00" EndTime="22/07/2022 12:43:48 PM" ExpectedStatus="PASS" FinalStatus="PASS" ID="86" Name="Succesfully clicked on image1.jpg" StartTime="22/07/2022 12:43:48 PM"><Log Duration="00:00:00" EndTime="22/07/2022 12:43:48 PM" Name="CLICK" StartTime="22/07/2022 12:43:48 PM" Status="PASS" Type="click on the object"/></TestStep><TestStep ActualStatus="PASS" Duration="00:00:00" EndTime="22/07/2022 12:43:51 PM" ExpectedStatus="PASS" FinalStatus="PASS" ID="87" Name="Succesfully uploaded file  upload" StartTime="22/07/2022 12:43:51 PM"><Log Duration="00:00:00" EndTime="22/07/2022 12:43:51 PM" Name="UPLOAD_FILE" StartTime="22/07/2022 12:43:51 PM" Status="PASS" Type="Upload_File  "/></TestStep><TestStep ActualStatus="PASS" Duration="00:00:00" EndTime="22/07/2022 12:44:14 PM" ExpectedStatus="PASS" FinalStatus="PASS" ID="88" Name="Succesfully clicked on image2.jpg" StartTime="22/07/2022 12:44:14 PM"><Log Duration="00:00:00" EndTime="22/07/2022 12:44:14 PM" Name="CLICK" StartTime="22/07/2022 12:44:14 PM" Status="PASS" Type="click on the object"/></TestStep><TestStep ActualStatus="PASS" Duration="00:00:00" EndTime="22/07/2022 12:44:17 PM" ExpectedStatus="PASS" FinalStatus="PASS" ID="89" Name="Succesfully uploaded file  upload1" StartTime="22/07/2022 12:44:17 PM"><Log Duration="00:00:00" EndTime="22/07/2022 12:44:17 PM" Name="UPLOAD_FILE" StartTime="22/07/2022 12:44:17 PM" Status="PASS" Type="Upload_File  "/></TestStep><TestStep ActualStatus="PASS" Duration="00:00:00" EndTime="22/07/2022 12:44:40 PM" ExpectedStatus="PASS" FinalStatus="PASS" ID="90" Name="Succesfully clicked on GMARBLES.JPG" StartTime="22/07/2022 12:44:40 PM"><Log Duration="00:00:00" EndTime="22/07/2022 12:44:40 PM" Name="CLICK" StartTime="22/07/2022 12:44:40 PM" Status="PASS" Type="click on the object"/></TestStep><TestStep ActualStatus="PASS" Duration="00:00:00" EndTime="22/07/2022 12:44:44 PM" ExpectedStatus="PASS" FinalStatus="PASS" ID="91" Name="Succesfully uploaded file  upload2" StartTime="22/07/2022 12:44:44 PM"><Log Duration="00:00:00" EndTime="22/07/2022 12:44:44 PM" Name="UPLOAD_FILE" StartTime="22/07/2022 12:44:44 PM" Status="PASS" Type="Upload_File  "/></TestStep><TestStep ActualStatus="PASS" Duration="00:00:00" EndTime="22/07/2022 12:45:07 PM" ExpectedStatus="PASS" FinalStatus="PASS" ID="92" Name="Succesfully clicked on image1.jpg" StartTime="22/07/2022 12:45:07 PM"><Log Duration="00:00:00" EndTime="22/07/2022 12:45:07 PM" Name="CLICK" StartTime="22/07/2022 12:45:07 PM" Status="PASS" Type="click on the object"/></TestStep><TestStep ActualStatus="PASS" Duration="00:00:00" EndTime="22/07/2022 12:45:10 PM" ExpectedStatus="PASS" FinalStatus="PASS" ID="93" Name="Succesfully uploaded file  upload" StartTime="22/07/2022 12:45:10 PM"><Log Duration="00:00:00" EndTime="22/07/2022 12:45:10 PM" Name="UPLOAD_FILE" StartTime="22/07/2022 12:45:10 PM" Status="PASS" Type="Upload_File  "/></TestStep><TestStep ActualStatus="FAIL" Duration="00:00:00" EndTime="22/07/2022 12:45:34 PM" ExpectedStatus="PASS" FinalStatus="FAIL" ID="94" Name="unable to find the locator " StartTime="22/07/2022 12:45:34 PM"><Log Duration="00:00:00" EndTime="22/07/2022 12:45:34 PM" Name="CLICK" Screenshot="img/screenshots/12-45-34Screenshot.jpg" StartTime="22/07/2022 12:45:34 PM" Status="FAIL" Type="click on the object"/></TestStep></TestCase></TestSuite><Project Duration="00:06:30" EndTime="22/07/2022 12:45:34 PM" Name="Selenium Framework" StartTime="22/07/2022 12:39:04 PM" Status="FAIL"><EnvironmentDetails HostName="ekoy-test.fa.em2.oraclecloud.com" InstanceName="ekoy-Test" ThresholdValue="90" URL="https://ekoy-test.fa.em2.oraclecloud.com/" UserName="Vignesh"/></Project></AutomationReportViewer>